phoenixquant
