Metadata-Version: 1.2
Name: phoenixquant
Version: 1.13
Summary: This is PhoenixQuant API
Home-page: https://www.phoenixquant.com
Author: Aaron Qiu
Author-email: chiminyau@gmail.com
License: MIT
Platform: UNKNOWN
Classifier: Programming Language :: Python :: 3
Classifier: License :: OSI Approved :: MIT License
Requires-Python: >=3
